appcenter/__init__.py
appcenter/analytics.py
appcenter/apps.py
appcenter/constants.py
appcenter/crashes.py
appcenter/derived_client.py
appcenter/models.py
appcenter/orgs.py
appcenter/orgs_teams.py
appcenter/py.typed
appcenter/tokens.py
appcenter/versions.py
appcenter-6.0.0.dist-info/LICENSE
appcenter-6.0.0.dist-info/METADATA
appcenter-6.0.0.dist-info/WHEEL
appcenter-6.0.0.dist-info/RECORD
