Metadata-Version: 2.1
Name: appcenter
Version: 6.0.0
Summary: A Python wrapper around the App Center REST API.
Home-page: https://github.com/Microsoft/appcenter-rest-python
License: MIT
Keywords: app center,api
Author: Dale Myers
Author-email: dalemy@microsoft.com
Requires-Python: >=3.11,<4.0
Classifier: Development Status :: 4 - Beta
Classifier: Intended Audience :: Developers
Classifier: License :: OSI Approved :: MIT License
Classifier: Programming Language :: Python :: 3
Classifier: Programming Language :: Python :: 3.11
Classifier: Programming Language :: Python :: 3.12
Classifier: Programming Language :: Python :: 3.13
Classifier: Programming Language :: Python :: 3.14
Classifier: Topic :: Software Development
Classifier: Topic :: Utilities
Requires-Dist: azure-storage-blob (>=12.13.0,<13.0.0)
Requires-Dist: deserialize (>=2.0.1,<3.0.0)
Requires-Dist: requests (>=2.32.0,<3.0.0)
Requires-Dist: tenacity (>=8.2.2,<9.0.0)
Requires-Dist: types-requests (>=2.32.0.20240602,<3.0.0.0)
Project-URL: Repository, https://github.com/Microsoft/appcenter-rest-python
